dataspec/__init__.py
dataspec/__version__.py
dataspec/api.py
dataspec/base.py
dataspec/factories.py
dataspec/__pycache__/__init__.cpython-36.pyc
dataspec/__pycache__/api.cpython-36.pyc
dataspec/__pycache__/base.cpython-36.pyc
dataspec/__pycache__/factories.cpython-36.pyc
dataspec-0.3.2.dist-info/LICENSE
dataspec-0.3.2.dist-info/METADATA
dataspec-0.3.2.dist-info/WHEEL
dataspec-0.3.2.dist-info/top_level.txt
dataspec-0.3.2.dist-info/RECORD
