Metadata-Version: 2.1
Name: dataspec
Version: 0.3.2
Summary: Data specification and normalization toolkit
Home-page: http://github.com/coverahealth/dataspec
Author: Covera Health
Author-email: engineering@coverahealth.com
License: MIT License
Platform: UNKNOWN
Classifier: Development Status :: 3 - Alpha
Classifier: Intended Audience :: Developers
Classifier: License :: OSI Approved :: MIT License
Classifier: Programming Language :: Python
Classifier: Programming Language :: Python :: 3
Classifier: Programming Language :: Python :: 3.6
Classifier: Programming Language :: Python :: 3.7
Classifier: Programming Language :: Python :: 3.8
Classifier: Programming Language :: Python :: Implementation :: CPython
Classifier: Topic :: Software Development :: Libraries
Requires-Python: >=3.6.0
Requires-Dist: attrs
Provides-Extra: dates
Requires-Dist: python-dateutil ; extra == 'dates'
Provides-Extra: phonenumbers
Requires-Dist: phonenumbers ; extra == 'phonenumbers'
